quark_sphinx_theme/__init__.py
quark_sphinx_theme/_lovelace.py
quark_sphinx_theme/ext/__init__.py
quark_sphinx_theme/ext/html_compat.py
quark_sphinx_theme/ext/html_rewrite/__init__.py
quark_sphinx_theme/ext/html_rewrite/boxes.py
quark_sphinx_theme/ext/html_rewrite/compat.py
quark_sphinx_theme/ext/html_rewrite/literal_blocks.py
quark_sphinx_theme/quark/domainindex.html
quark_sphinx_theme/quark/genindex-single.html
quark_sphinx_theme/quark/genindex.html
quark_sphinx_theme/quark/layout.html
quark_sphinx_theme/quark/theme.conf
quark_sphinx_theme/quark/static/quark.css_t
quark_sphinx_theme-0.6.0.dist-info/entry_points.txt
quark_sphinx_theme-0.6.0.dist-info/LICENSE
quark_sphinx_theme-0.6.0.dist-info/WHEEL
quark_sphinx_theme-0.6.0.dist-info/METADATA
quark_sphinx_theme-0.6.0.dist-info/RECORD
