Metadata-Version: 2.1
Name: quark-sphinx-theme
Version: 0.6.0
Summary: A Sphinx theme designed for QTextBrowser
Home-page: https://gitlab.com/fkrull/quark-sphinx-theme
License: UNKNOWN
Author: Felix Krull
Author-email: f_krull@gmx.de
Requires-Python: >= 3.5
Classifier: Development Status :: 4 - Beta
Classifier: Framework :: Sphinx :: Theme
Classifier: Intended Audience :: Developers
Classifier: License :: OSI Approved :: BSD License
Classifier: Operating System :: OS Independent
Classifier: Programming Language :: Python :: 3
Classifier: Topic :: Documentation :: Sphinx
Classifier: Topic :: Software Development :: Documentation
Requires-Dist: sphinx >= 1.8
Requires-Dist: html5lib ; extra == "test"
Requires-Dist: tinycss ; extra == "test"
Provides-Extra: test
